nonebot_plugin_picsetu/__init__.py
nonebot_plugin_picsetu-0.0.4.dist-info/METADATA
nonebot_plugin_picsetu-0.0.4.dist-info/WHEEL
nonebot_plugin_picsetu-0.0.4.dist-info/top_level.txt
nonebot_plugin_picsetu-0.0.4.dist-info/RECORD
