Metadata-Version: 2.1
Name: nonebot_plugin_picsetu
Version: 0.0.4
Summary: Default template for PDM package
Author-email: zhongwen-4 <2401128923@qq.com>
License: MIT
Requires-Python: >=3.10
Requires-Dist: nonebot2 >=2.3.3
Requires-Dist: nonebot-adapter-onebot >=2.4.5
Requires-Dist: httpx >=0.27.2
